birds/.DS_Store
birds/__init__.py
birds-0.0.2.dist-info/WHEEL
birds-0.0.2.dist-info/METADATA
birds-0.0.2.dist-info/RECORD
