Metadata-Version: 2.1
Name: birds
Version: 0.0.2
Summary: birds
Author-email: Alyetama <56323389+Alyetama@users.noreply.github.com>
Classifier: License :: OSI Approved :: MIT License
Project-URL: Home, https://github.comm/Alyetama/birds
